[
  {
    "repo": "silships/figma-cli",
    "branch": "main",
    "language": "JavaScript",
    "description": ""
  },
  {
    "repo": "fancyai-official/skills",
    "branch": "main",
    "language": "Python",
    "description": ""
  },
  {
    "repo": "soloterm/screen",
    "branch": "main",
    "language": "PHP",
    "description": "A terminal renderer written in pure PHP."
  },
  {
    "repo": "python-pillow/Pillow",
    "branch": "main",
    "language": "Python",
    "description": "Python Imaging Library (Fork)"
  },
  {
    "repo": "expressjs/express",
    "branch": "master",
    "language": "JavaScript",
    "description": "Fast, unopinionated, minimalist web framework for node."
  },
  {
    "repo": "getsentry/sentry-javascript",
    "branch": "develop",
    "language": "TypeScript",
    "description": "Official Sentry SDKs for JavaScript"
  },
  {
    "repo": "square/retrofit",
    "branch": "master",
    "language": "HTML",
    "description": "A type-safe HTTP client for Android and the JVM"
  },
  {
    "repo": "mermaid-js/mermaid",
    "branch": "develop",
    "language": "TypeScript",
    "description": "Generation of diagrams like flowcharts or sequence diagrams from text in a similar manner as markdown"
  },
  {
    "repo": "996icu/996.ICU",
    "branch": "master",
    "language": "Other",
    "description": "Repo for counting stars and contributing. Press F to pay respect to glorious developers."
  },
  {
    "repo": "sympy/sympy",
    "branch": "master",
    "language": "Python",
    "description": "A computer algebra system written in pure Python"
  },
  {
    "repo": "tox-dev/tox",
    "branch": "main",
    "language": "Python",
    "description": "Command line driven CI frontend and development task automation tool."
  },
  {
    "repo": "androidx/media",
    "branch": "main",
    "language": "Java",
    "description": "Jetpack Media3 support libraries for media use cases, including ExoPlayer, an extensible media player for Android"
  },
  {
    "repo": "requests/requests",
    "branch": "main",
    "language": "Python",
    "description": "A simple, yet elegant, HTTP library."
  },
  {
    "repo": "home-assistant/core",
    "branch": "dev",
    "language": "Python",
    "description": ":house_with_garden: Open source home automation that puts local control and privacy first."
  },
  {
    "repo": "rust-lang/rust",
    "branch": "master",
    "language": "Rust",
    "description": "Empowering everyone to build reliable and efficient software."
  },
  {
    "repo": "facebookresearch/fairseq",
    "branch": "main",
    "language": "Python",
    "description": "Facebook AI Research Sequence-to-Sequence Toolkit written in Python."
  },
  {
    "repo": "airbnb/javascript",
    "branch": "master",
    "language": "JavaScript",
    "description": "JavaScript Style Guide"
  },
  {
    "repo": "nedbat/coveragepy",
    "branch": "master",
    "language": "Python",
    "description": "The code coverage tool for Python"
  },
  {
    "repo": "scrapy/scrapy",
    "branch": "master",
    "language": "Python",
    "description": "Scrapy, a fast high-level web crawling & scraping framework for Python."
  },
  {
    "repo": "explosion/spaCy",
    "branch": "master",
    "language": "Python",
    "description": "💫 Industrial-strength Natural Language Processing (NLP) in Python"
  },
  {
    "repo": "animate-css/animate.css",
    "branch": "main",
    "language": "CSS",
    "description": "🍿 A cross-browser library of CSS animations. As easy to use as an easy thing."
  },
  {
    "repo": "vim/vim",
    "branch": "master",
    "language": "Vim Script",
    "description": "The official Vim repository"
  },
  {
    "repo": "nocodb/nocodb",
    "branch": "develop",
    "language": "TypeScript",
    "description": "🔥 🔥 🔥 A Free & Self-hostable Airtable Alternative"
  },
  {
    "repo": "mrdoob/draco.js",
    "branch": "main",
    "language": "JavaScript",
    "description": "A small, drop-in, pure-JavaScript Draco mesh loader for three.js."
  }
]